{
  "last_run_at": "2026-04-11T22:17:23.813848Z",
  "snapshots": [
    [
      {
        "id": 22516,
        "time": 1759884179.8425376,
        "is_full_data": false,
        "buy_offer": -1,
        "sell_offer": -1,
        "month_average_sell": -1,
        "month_average_buy": -1,
        "month_sold": -1,
        "month_bought": -1,
        "active_traders": -1,
        "month_highest_sell": -1,
        "month_lowest_buy": -1,
        "month_lowest_sell": -1,
        "month_highest_buy": -1,
        "buy_offers": -1,
        "sell_offers": -1,
        "day_average_sell": 39249,
        "day_average_buy": 33333,
        "day_sold": 4,
        "day_bought": 3,
        "day_highest_sell": 40000,
        "day_lowest_sell": 38000,
        "day_highest_buy": 35000,
        "day_lowest_buy": 30001,
        "total_immediate_profit": -1,
        "total_immediate_profit_info": ""
      },
      {
        "id": 22516,
        "time": 1760143379.843589,
        "is_full_data": true,
        "buy_offer": 30001,
        "sell_offer": 39800,
        "month_average_sell": 37642,
        "month_average_buy": 29444,
        "month_sold": 63,
        "month_bought": 5,
        "active_traders": 1,
        "month_highest_sell": 44995,
        "month_lowest_buy": 25000,
        "month_lowest_sell": 31500,
        "month_highest_buy": 35000,
        "buy_offers": 1,
        "sell_offers": 6,
        "day_average_sell": 39899,
        "day_average_buy": 30001,
        "day_sold": 5,
        "day_bought": 1,
        "day_highest_sell": 39999,
        "day_lowest_sell": 39500,
        "day_highest_buy": 30001,
        "day_lowest_buy": 30001,
        "total_immediate_profit": 0,
        "total_immediate_profit_info": ""
      },
      {
        "id": 22516,
        "time": 1760647338.7967122,
        "is_full_data": false,
        "buy_offer": -1,
        "sell_offer": -1,
        "month_average_sell": -1,
        "month_average_buy": -1,
        "month_sold": -1,
        "month_bought": -1,
        "active_traders": -1,
        "month_highest_sell": -1,
        "month_lowest_buy": -1,
        "month_lowest_sell": -1,
        "month_highest_buy": -1,
        "buy_offers": -1,
        "sell_offers": -1,
        "day_average_sell": 33833,
        "day_average_buy": 31000,
        "day_sold": 3,
        "day_bought": 4,
        "day_highest_sell": 35000,
        "day_lowest_sell": 32500,
        "day_highest_buy": 31001,
        "day_lowest_buy": 31000,
        "total_immediate_profit": -1,
        "total_immediate_profit_info": ""
      },
      {
        "id": 22516,
        "time": 1761601355.0362985,
        "is_full_data": false,
        "buy_offer": -1,
        "sell_offer": -1,
        "month_average_sell": -1,
        "month_average_buy": -1,
        "month_sold": -1,
        "month_bought": -1,
        "active_traders": -1,
        "month_highest_sell": -1,
        "month_lowest_buy": -1,
        "month_lowest_sell": -1,
        "month_highest_buy": -1,
        "buy_offers": -1,
        "sell_offers": -1,
        "day_average_sell": 40625,
        "day_average_buy": 30000,
        "day_sold": 4,
        "day_bought": 1,
        "day_highest_sell": 44000,
        "day_lowest_sell": 39000,
        "day_highest_buy": 30000,
        "day_lowest_buy": 30000,
        "total_immediate_profit": -1,
        "total_immediate_profit_info": ""
      },
      {
        "id": 22516,
        "time": 1762119755.0360663,
        "is_full_data": false,
        "buy_offer": -1,
        "sell_offer": -1,
        "month_average_sell": -1,
        "month_average_buy": -1,
        "month_sold": -1,
        "month_bought": -1,
        "active_traders": -1,
        "month_highest_sell": -1,
        "month_lowest_buy": -1,
        "month_lowest_sell": -1,
        "month_highest_buy": -1,
        "buy_offers": -1,
        "sell_offers": -1,
        "day_average_sell": 44369,
        "day_average_buy": 33000,
        "day_sold": 3,
        "day_bought": 1,
        "day_highest_sell": 45999,
        "day_lowest_sell": 41111,
        "day_highest_buy": 33000,
        "day_lowest_buy": 33000,
        "total_immediate_profit": -1,
        "total_immediate_profit_info": ""
      },
      {
        "id": 22516,
        "time": 1763761342.1336908,
        "is_full_data": false,
        "buy_offer": -1,
        "sell_offer": -1,
        "month_average_sell": -1,
        "month_average_buy": -1,
        "month_sold": -1,
        "month_bought": -1,
        "active_traders": -1,
        "month_highest_sell": -1,
        "month_lowest_buy": -1,
        "month_lowest_sell": -1,
        "month_highest_buy": -1,
        "buy_offers": -1,
        "sell_offers": -1,
        "day_average_sell": 59600,
        "day_average_buy": 40000,
        "day_sold": 1,
        "day_bought": 1,
        "day_highest_sell": 59600,
        "day_lowest_sell": 59600,
        "day_highest_buy": 40000,
        "day_lowest_buy": 40000,
        "total_immediate_profit": -1,
        "total_immediate_profit_info": ""
      },
      {
        "id": 22516,
        "time": 1764538993.5885456,
        "is_full_data": false,
        "buy_offer": -1,
        "sell_offer": -1,
        "month_average_sell": -1,
        "month_average_buy": -1,
        "month_sold": -1,
        "month_bought": -1,
        "active_traders": -1,
        "month_highest_sell": -1,
        "month_lowest_buy": -1,
        "month_lowest_sell": -1,
        "month_highest_buy": -1,
        "buy_offers": -1,
        "sell_offers": -1,
        "day_average_sell": 55018,
        "day_average_buy": 40000,
        "day_sold": 3,
        "day_bought": 1,
        "day_highest_sell": 55555,
        "day_lowest_sell": 54000,
        "day_highest_buy": 40000,
        "day_lowest_buy": 40000,
        "total_immediate_profit": -1,
        "total_immediate_profit_info": ""
      },
      {
        "id": 22516,
        "time": 1766353405.2878098,
        "is_full_data": false,
        "buy_offer": -1,
        "sell_offer": -1,
        "month_average_sell": -1,
        "month_average_buy": -1,
        "month_sold": -1,
        "month_bought": -1,
        "active_traders": -1,
        "month_highest_sell": -1,
        "month_lowest_buy": -1,
        "month_lowest_sell": -1,
        "month_highest_buy": -1,
        "buy_offers": -1,
        "sell_offers": -1,
        "day_average_sell": 48437,
        "day_average_buy": 36000,
        "day_sold": 4,
        "day_bought": 1,
        "day_highest_sell": 48500,
        "day_lowest_sell": 48250,
        "day_highest_buy": 36000,
        "day_lowest_buy": 36000,
        "total_immediate_profit": -1,
        "total_immediate_profit_info": ""
      },
      {
        "id": 22516,
        "time": 1767478523.2050726,
        "is_full_data": false,
        "buy_offer": -1,
        "sell_offer": -1,
        "month_average_sell": -1,
        "month_average_buy": -1,
        "month_sold": -1,
        "month_bought": -1,
        "active_traders": -1,
        "month_highest_sell": -1,
        "month_lowest_buy": -1,
        "month_lowest_sell": -1,
        "month_highest_buy": -1,
        "buy_offers": -1,
        "sell_offers": -1,
        "day_average_sell": 44500,
        "day_average_buy": 32500,
        "day_sold": 2,
        "day_bought": 1,
        "day_highest_sell": 45000,
        "day_lowest_sell": 44000,
        "day_highest_buy": 32500,
        "day_lowest_buy": 32500,
        "total_immediate_profit": -1,
        "total_immediate_profit_info": ""
      },
      {
        "id": 22516,
        "time": 1767564923.2050369,
        "is_full_data": false,
        "buy_offer": -1,
        "sell_offer": -1,
        "month_average_sell": -1,
        "month_average_buy": -1,
        "month_sold": -1,
        "month_bought": -1,
        "active_traders": -1,
        "month_highest_sell": -1,
        "month_lowest_buy": -1,
        "month_lowest_sell": -1,
        "month_highest_buy": -1,
        "buy_offers": -1,
        "sell_offers": -1,
        "day_average_sell": 41995,
        "day_average_buy": 32500,
        "day_sold": 2,
        "day_bought": 1,
        "day_highest_sell": 41995,
        "day_lowest_sell": 41995,
        "day_highest_buy": 32500,
        "day_lowest_buy": 32500,
        "total_immediate_profit": -1,
        "total_immediate_profit_info": ""
      },
      {
        "id": 22516,
        "time": 1769290990.2978127,
        "is_full_data": false,
        "buy_offer": -1,
        "sell_offer": -1,
        "month_average_sell": -1,
        "month_average_buy": -1,
        "month_sold": -1,
        "month_bought": -1,
        "active_traders": -1,
        "month_highest_sell": -1,
        "month_lowest_buy": -1,
        "month_lowest_sell": -1,
        "month_highest_buy": -1,
        "buy_offers": -1,
        "sell_offers": -1,
        "day_average_sell": 42000,
        "day_average_buy": 31000,
        "day_sold": 1,
        "day_bought": 1,
        "day_highest_sell": 42000,
        "day_lowest_sell": 42000,
        "day_highest_buy": 31000,
        "day_lowest_buy": 31000,
        "total_immediate_profit": -1,
        "total_immediate_profit_info": ""
      },
      {
        "id": 22516,
        "time": 1769724683.4968445,
        "is_full_data": false,
        "buy_offer": -1,
        "sell_offer": -1,
        "month_average_sell": -1,
        "month_average_buy": -1,
        "month_sold": -1,
        "month_bought": -1,
        "active_traders": -1,
        "month_highest_sell": -1,
        "month_lowest_buy": -1,
        "month_lowest_sell": -1,
        "month_highest_buy": -1,
        "buy_offers": -1,
        "sell_offers": -1,
        "day_average_sell": 39800,
        "day_average_buy": 31000,
        "day_sold": 1,
        "day_bought": 1,
        "day_highest_sell": 39800,
        "day_lowest_sell": 39800,
        "day_highest_buy": 31000,
        "day_lowest_buy": 31000,
        "total_immediate_profit": -1,
        "total_immediate_profit_info": ""
      },
      {
        "id": 22516,
        "time": 1770241389.8098092,
        "is_full_data": false,
        "buy_offer": -1,
        "sell_offer": -1,
        "month_average_sell": -1,
        "month_average_buy": -1,
        "month_sold": -1,
        "month_bought": -1,
        "active_traders": -1,
        "month_highest_sell": -1,
        "month_lowest_buy": -1,
        "month_lowest_sell": -1,
        "month_highest_buy": -1,
        "buy_offers": -1,
        "sell_offers": -1,
        "day_average_sell": 38000,
        "day_average_buy": 30500,
        "day_sold": 3,
        "day_bought": 2,
        "day_highest_sell": 38000,
        "day_lowest_sell": 38000,
        "day_highest_buy": 31000,
        "day_lowest_buy": 30000,
        "total_immediate_profit": -1,
        "total_immediate_profit_info": ""
      },
      {
        "id": 22516,
        "time": 1770500589.8096852,
        "is_full_data": false,
        "buy_offer": -1,
        "sell_offer": -1,
        "month_average_sell": -1,
        "month_average_buy": -1,
        "month_sold": -1,
        "month_bought": -1,
        "active_traders": -1,
        "month_highest_sell": -1,
        "month_lowest_buy": -1,
        "month_lowest_sell": -1,
        "month_highest_buy": -1,
        "buy_offers": -1,
        "sell_offers": -1,
        "day_average_sell": 35000,
        "day_average_buy": 30000,
        "day_sold": 1,
        "day_bought": 1,
        "day_highest_sell": 35000,
        "day_lowest_sell": 35000,
        "day_highest_buy": 30000,
        "day_lowest_buy": 30000,
        "total_immediate_profit": -1,
        "total_immediate_profit_info": ""
      },
      {
        "id": 22516,
        "time": 1770932589.809502,
        "is_full_data": false,
        "buy_offer": -1,
        "sell_offer": -1,
        "month_average_sell": -1,
        "month_average_buy": -1,
        "month_sold": -1,
        "month_bought": -1,
        "active_traders": -1,
        "month_highest_sell": -1,
        "month_lowest_buy": -1,
        "month_lowest_sell": -1,
        "month_highest_buy": -1,
        "buy_offers": -1,
        "sell_offers": -1,
        "day_average_sell": 35000,
        "day_average_buy": 30000,
        "day_sold": 1,
        "day_bought": 1,
        "day_highest_sell": 35000,
        "day_lowest_sell": 35000,
        "day_highest_buy": 30000,
        "day_lowest_buy": 30000,
        "total_immediate_profit": -1,
        "total_immediate_profit_info": ""
      },
      {
        "id": 22516,
        "time": 1771018989.810587,
        "is_full_data": true,
        "buy_offer": 30000,
        "sell_offer": 37665,
        "month_average_sell": 39429,
        "month_average_buy": 30416,
        "month_sold": 34,
        "month_bought": 7,
        "active_traders": 2,
        "month_highest_sell": 48000,
        "month_lowest_buy": 30000,
        "month_lowest_sell": 35000,
        "month_highest_buy": 31000,
        "buy_offers": 2,
        "sell_offers": 6,
        "day_average_sell": 36776,
        "day_average_buy": 30000,
        "day_sold": 3,
        "day_bought": 1,
        "day_highest_sell": 37665,
        "day_lowest_sell": 35000,
        "day_highest_buy": 30000,
        "day_lowest_buy": 30000,
        "total_immediate_profit": 0,
        "total_immediate_profit_info": ""
      },
      {
        "id": 22516,
        "time": 1771105396.3705785,
        "is_full_data": false,
        "buy_offer": -1,
        "sell_offer": -1,
        "month_average_sell": -1,
        "month_average_buy": -1,
        "month_sold": -1,
        "month_bought": -1,
        "active_traders": -1,
        "month_highest_sell": -1,
        "month_lowest_buy": -1,
        "month_lowest_sell": -1,
        "month_highest_buy": -1,
        "buy_offers": -1,
        "sell_offers": -1,
        "day_average_sell": 36776,
        "day_average_buy": 30000,
        "day_sold": 3,
        "day_bought": 1,
        "day_highest_sell": 37665,
        "day_lowest_sell": 35000,
        "day_highest_buy": 30000,
        "day_lowest_buy": 30000,
        "total_immediate_profit": -1,
        "total_immediate_profit_info": ""
      },
      {
        "id": 22516,
        "time": 1771969498.1830566,
        "is_full_data": false,
        "buy_offer": -1,
        "sell_offer": -1,
        "month_average_sell": -1,
        "month_average_buy": -1,
        "month_sold": -1,
        "month_bought": -1,
        "active_traders": -1,
        "month_highest_sell": -1,
        "month_lowest_buy": -1,
        "month_lowest_sell": -1,
        "month_highest_buy": -1,
        "buy_offers": -1,
        "sell_offers": -1,
        "day_average_sell": 41992,
        "day_average_buy": 30000,
        "day_sold": 2,
        "day_bought": 1,
        "day_highest_sell": 41995,
        "day_lowest_sell": 41990,
        "day_highest_buy": 30000,
        "day_lowest_buy": 30000,
        "total_immediate_profit": -1,
        "total_immediate_profit_info": ""
      },
      {
        "id": 22516,
        "time": 1773006361.8909755,
        "is_full_data": false,
        "buy_offer": -1,
        "sell_offer": -1,
        "month_average_sell": -1,
        "month_average_buy": -1,
        "month_sold": -1,
        "month_bought": -1,
        "active_traders": -1,
        "month_highest_sell": -1,
        "month_lowest_buy": -1,
        "month_lowest_sell": -1,
        "month_highest_buy": -1,
        "buy_offers": -1,
        "sell_offers": -1,
        "day_average_sell": 51031,
        "day_average_buy": 40000,
        "day_sold": 6,
        "day_bought": 2,
        "day_highest_sell": 59900,
        "day_lowest_sell": 45444,
        "day_highest_buy": 40000,
        "day_lowest_buy": 40000,
        "total_immediate_profit": -1,
        "total_immediate_profit_info": ""
      },
      {
        "id": 22516,
        "time": 1773092761.890952,
        "is_full_data": false,
        "buy_offer": -1,
        "sell_offer": -1,
        "month_average_sell": -1,
        "month_average_buy": -1,
        "month_sold": -1,
        "month_bought": -1,
        "active_traders": -1,
        "month_highest_sell": -1,
        "month_lowest_buy": -1,
        "month_lowest_sell": -1,
        "month_highest_buy": -1,
        "buy_offers": -1,
        "sell_offers": -1,
        "day_average_sell": 55000,
        "day_average_buy": 41000,
        "day_sold": 1,
        "day_bought": 1,
        "day_highest_sell": 55000,
        "day_lowest_sell": 55000,
        "day_highest_buy": 41000,
        "day_lowest_buy": 41000,
        "total_immediate_profit": -1,
        "total_immediate_profit_info": ""
      },
      {
        "id": 22516,
        "time": 1773521057.0535831,
        "is_full_data": false,
        "buy_offer": -1,
        "sell_offer": -1,
        "month_average_sell": -1,
        "month_average_buy": -1,
        "month_sold": -1,
        "month_bought": -1,
        "active_traders": -1,
        "month_highest_sell": -1,
        "month_lowest_buy": -1,
        "month_lowest_sell": -1,
        "month_highest_buy": -1,
        "buy_offers": -1,
        "sell_offers": -1,
        "day_average_sell": 54000,
        "day_average_buy": 45000,
        "day_sold": 2,
        "day_bought": 1,
        "day_highest_sell": 55000,
        "day_lowest_sell": 53000,
        "day_highest_buy": 45000,
        "day_lowest_buy": 45000,
        "total_immediate_profit": -1,
        "total_immediate_profit_info": ""
      },
      {
        "id": 22516,
        "time": 1774039457.0534601,
        "is_full_data": false,
        "buy_offer": -1,
        "sell_offer": -1,
        "month_average_sell": -1,
        "month_average_buy": -1,
        "month_sold": -1,
        "month_bought": -1,
        "active_traders": -1,
        "month_highest_sell": -1,
        "month_lowest_buy": -1,
        "month_lowest_sell": -1,
        "month_highest_buy": -1,
        "buy_offers": -1,
        "sell_offers": -1,
        "day_average_sell": 54500,
        "day_average_buy": 42500,
        "day_sold": 2,
        "day_bought": 1,
        "day_highest_sell": 55000,
        "day_lowest_sell": 54000,
        "day_highest_buy": 42500,
        "day_lowest_buy": 42500,
        "total_immediate_profit": -1,
        "total_immediate_profit_info": ""
      },
      {
        "id": 22516,
        "time": 1774125857.054063,
        "is_full_data": true,
        "buy_offer": 45000,
        "sell_offer": 61000,
        "month_average_sell": 47064,
        "month_average_buy": 40222,
        "month_sold": 54,
        "month_bought": 12,
        "active_traders": 3,
        "month_highest_sell": 61000,
        "month_lowest_buy": 30000,
        "month_lowest_sell": 35000,
        "month_highest_buy": 45000,
        "buy_offers": 5,
        "sell_offers": 3,
        "day_average_sell": 60266,
        "day_average_buy": 45000,
        "day_sold": 3,
        "day_bought": 1,
        "day_highest_sell": 61000,
        "day_lowest_sell": 59900,
        "day_highest_buy": 45000,
        "day_lowest_buy": 45000,
        "total_immediate_profit": 0,
        "total_immediate_profit_info": ""
      },
      {
        "id": 22516,
        "time": 1774381451.9051754,
        "is_full_data": false,
        "buy_offer": -1,
        "sell_offer": -1,
        "month_average_sell": -1,
        "month_average_buy": -1,
        "month_sold": -1,
        "month_bought": -1,
        "active_traders": -1,
        "month_highest_sell": -1,
        "month_lowest_buy": -1,
        "month_lowest_sell": -1,
        "month_highest_buy": -1,
        "buy_offers": -1,
        "sell_offers": -1,
        "day_average_sell": 62966,
        "day_average_buy": 47500,
        "day_sold": 3,
        "day_bought": 2,
        "day_highest_sell": 64900,
        "day_lowest_sell": 61000,
        "day_highest_buy": 47500,
        "day_lowest_buy": 47500,
        "total_immediate_profit": -1,
        "total_immediate_profit_info": ""
      },
      {
        "id": 22516,
        "time": 1774727051.9050908,
        "is_full_data": false,
        "buy_offer": -1,
        "sell_offer": -1,
        "month_average_sell": -1,
        "month_average_buy": -1,
        "month_sold": -1,
        "month_bought": -1,
        "active_traders": -1,
        "month_highest_sell": -1,
        "month_lowest_buy": -1,
        "month_lowest_sell": -1,
        "month_highest_buy": -1,
        "buy_offers": -1,
        "sell_offers": -1,
        "day_average_sell": 50000,
        "day_average_buy": 49000,
        "day_sold": 1,
        "day_bought": 1,
        "day_highest_sell": 50000,
        "day_lowest_sell": 50000,
        "day_highest_buy": 49000,
        "day_lowest_buy": 49000,
        "total_immediate_profit": -1,
        "total_immediate_profit_info": ""
      },
      {
        "id": 22516,
        "time": 1774813451.9056976,
        "is_full_data": true,
        "buy_offer": 49100,
        "sell_offer": 63999,
        "month_average_sell": 52739,
        "month_average_buy": 43409,
        "month_sold": 53,
        "month_bought": 15,
        "active_traders": 7,
        "month_highest_sell": 65000,
        "month_lowest_buy": 30000,
        "month_lowest_sell": 40000,
        "month_highest_buy": 49000,
        "buy_offers": 8,
        "sell_offers": 7,
        "day_average_sell": 63000,
        "day_average_buy": 49000,
        "day_sold": 2,
        "day_bought": 1,
        "day_highest_sell": 63000,
        "day_lowest_sell": 63000,
        "day_highest_buy": 49000,
        "day_lowest_buy": 49000,
        "total_immediate_profit": 0,
        "total_immediate_profit_info": ""
      },
      {
        "id": 22516,
        "time": 1774986248.5575793,
        "is_full_data": false,
        "buy_offer": -1,
        "sell_offer": -1,
        "month_average_sell": -1,
        "month_average_buy": -1,
        "month_sold": -1,
        "month_bought": -1,
        "active_traders": -1,
        "month_highest_sell": -1,
        "month_lowest_buy": -1,
        "month_lowest_sell": -1,
        "month_highest_buy": -1,
        "buy_offers": -1,
        "sell_offers": -1,
        "day_average_sell": 62999,
        "day_average_buy": 49102,
        "day_sold": 2,
        "day_bought": 1,
        "day_highest_sell": 63000,
        "day_lowest_sell": 62999,
        "day_highest_buy": 49102,
        "day_lowest_buy": 49102,
        "total_immediate_profit": -1,
        "total_immediate_profit_info": ""
      },
      {
        "id": 22516,
        "time": 1775072648.557538,
        "is_full_data": false,
        "buy_offer": -1,
        "sell_offer": -1,
        "month_average_sell": -1,
        "month_average_buy": -1,
        "month_sold": -1,
        "month_bought": -1,
        "active_traders": -1,
        "month_highest_sell": -1,
        "month_lowest_buy": -1,
        "month_lowest_sell": -1,
        "month_highest_buy": -1,
        "buy_offers": -1,
        "sell_offers": -1,
        "day_average_sell": 64331,
        "day_average_buy": 49075,
        "day_sold": 3,
        "day_bought": 4,
        "day_highest_sell": 64997,
        "day_lowest_sell": 63999,
        "day_highest_buy": 49102,
        "day_lowest_buy": 49000,
        "total_immediate_profit": -1,
        "total_immediate_profit_info": ""
      },
      {
        "id": 22516,
        "time": 1775331848.5574267,
        "is_full_data": false,
        "buy_offer": -1,
        "sell_offer": -1,
        "month_average_sell": -1,
        "month_average_buy": -1,
        "month_sold": -1,
        "month_bought": -1,
        "active_traders": -1,
        "month_highest_sell": -1,
        "month_lowest_buy": -1,
        "month_lowest_sell": -1,
        "month_highest_buy": -1,
        "buy_offers": -1,
        "sell_offers": -1,
        "day_average_sell": 63999,
        "day_average_buy": 42003,
        "day_sold": 10,
        "day_bought": 3,
        "day_highest_sell": 69000,
        "day_lowest_sell": 61999,
        "day_highest_buy": 42004,
        "day_lowest_buy": 42002,
        "total_immediate_profit": -1,
        "total_immediate_profit_info": ""
      }
    ]
  ],
  "_outlier_cleanup": {
    "version": 1,
    "lower_percentile": 1.5,
    "upper_percentile": 98.5,
    "window_size": 0,
    "accepted_fingerprints": [
      "0d29ef4429c0ddcc",
      "1958b5230b4895a3",
      "2eb9def1ffa2200a",
      "2f01da866bb4b56b",
      "2f889279dbf47afe",
      "310af59f63ecef25",
      "329e3de8b114b79d",
      "379c3ca28352a4c2",
      "3bd7bb807e11b62e",
      "4917887df3c3975f",
      "49339bfe4d3f3431",
      "4ce8b1c3e372f4c0",
      "55e67d7a14bdd432",
      "5a51d6330f3741d8",
      "6acbce142bd44f25",
      "8140de30fe592bb5",
      "8790b23c753cad42",
      "8a94817b9d6195a8",
      "8dc54d94aed15206",
      "a220442f7df62611",
      "ad085f504523d588",
      "ad27145c2facd8cc",
      "b038f86c706b1d18",
      "b77572c8cb16a7b9",
      "b82584b8ffeea050",
      "c6bd34f291dcf936",
      "dc99501fb9e63301",
      "f0db5d932e4b3e27",
      "f18c34885f1d1c6d"
    ],
    "rejected_fingerprints": [
      "23098d94717644de",
      "4123e82cd71b0ed6",
      "65fce0a410679a0f",
      "6b0d131ebf30f986",
      "7db157bb73b3dc78",
      "eb7eaeb6d411d71b",
      "f76347e2d268ef31"
    ]
  }
}
