{
  "last_run_at": "2026-04-11T20:43:34.833373Z",
  "snapshots": [
    [
      {
        "id": 22721,
        "time": 1762551813.0131419,
        "is_full_data": false,
        "buy_offer": -1,
        "sell_offer": -1,
        "month_average_sell": -1,
        "month_average_buy": -1,
        "month_sold": -1,
        "month_bought": -1,
        "active_traders": -1,
        "month_highest_sell": -1,
        "month_lowest_buy": -1,
        "month_lowest_sell": -1,
        "month_highest_buy": -1,
        "buy_offers": -1,
        "sell_offers": -1,
        "day_average_sell": 63163,
        "day_average_buy": 52506,
        "day_sold": 12,
        "day_bought": 7,
        "day_highest_sell": 63333,
        "day_lowest_sell": 62995,
        "day_highest_buy": 52512,
        "day_lowest_buy": 52502,
        "total_immediate_profit": -1,
        "total_immediate_profit_info": ""
      },
      {
        "id": 22721,
        "time": 1762897413.0130582,
        "is_full_data": false,
        "buy_offer": -1,
        "sell_offer": -1,
        "month_average_sell": -1,
        "month_average_buy": -1,
        "month_sold": -1,
        "month_bought": -1,
        "active_traders": -1,
        "month_highest_sell": -1,
        "month_lowest_buy": -1,
        "month_lowest_sell": -1,
        "month_highest_buy": -1,
        "buy_offers": -1,
        "sell_offers": -1,
        "day_average_sell": 63994,
        "day_average_buy": 52450,
        "day_sold": 10,
        "day_bought": 5,
        "day_highest_sell": 63998,
        "day_lowest_sell": 63990,
        "day_highest_buy": 53001,
        "day_lowest_buy": 52011,
        "total_immediate_profit": -1,
        "total_immediate_profit_info": ""
      },
      {
        "id": 22721,
        "time": 1762983813.0130384,
        "is_full_data": false,
        "buy_offer": -1,
        "sell_offer": -1,
        "month_average_sell": -1,
        "month_average_buy": -1,
        "month_sold": -1,
        "month_bought": -1,
        "active_traders": -1,
        "month_highest_sell": -1,
        "month_lowest_buy": -1,
        "month_lowest_sell": -1,
        "month_highest_buy": -1,
        "buy_offers": -1,
        "sell_offers": -1,
        "day_average_sell": 64624,
        "day_average_buy": 52244,
        "day_sold": 8,
        "day_bought": 1,
        "day_highest_sell": 65000,
        "day_lowest_sell": 63998,
        "day_highest_buy": 52244,
        "day_lowest_buy": 52244,
        "total_immediate_profit": -1,
        "total_immediate_profit_info": ""
      },
      {
        "id": 22721,
        "time": 1763070213.013018,
        "is_full_data": false,
        "buy_offer": -1,
        "sell_offer": -1,
        "month_average_sell": -1,
        "month_average_buy": -1,
        "month_sold": -1,
        "month_bought": -1,
        "active_traders": -1,
        "month_highest_sell": -1,
        "month_lowest_buy": -1,
        "month_lowest_sell": -1,
        "month_highest_buy": -1,
        "buy_offers": -1,
        "sell_offers": -1,
        "day_average_sell": 64994,
        "day_average_buy": 54746,
        "day_sold": 6,
        "day_bought": 15,
        "day_highest_sell": 64997,
        "day_lowest_sell": 64990,
        "day_highest_buy": 57002,
        "day_lowest_buy": 52252,
        "total_immediate_profit": -1,
        "total_immediate_profit_info": ""
      },
      {
        "id": 22721,
        "time": 1763156613.0129943,
        "is_full_data": false,
        "buy_offer": -1,
        "sell_offer": -1,
        "month_average_sell": -1,
        "month_average_buy": -1,
        "month_sold": -1,
        "month_bought": -1,
        "active_traders": -1,
        "month_highest_sell": -1,
        "month_lowest_buy": -1,
        "month_lowest_sell": -1,
        "month_highest_buy": -1,
        "buy_offers": -1,
        "sell_offers": -1,
        "day_average_sell": 64010,
        "day_average_buy": 52270,
        "day_sold": 7,
        "day_bought": 1,
        "day_highest_sell": 64989,
        "day_lowest_sell": 61885,
        "day_highest_buy": 52270,
        "day_lowest_buy": 52270,
        "total_immediate_profit": -1,
        "total_immediate_profit_info": ""
      },
      {
        "id": 22721,
        "time": 1763243013.012974,
        "is_full_data": false,
        "buy_offer": -1,
        "sell_offer": -1,
        "month_average_sell": -1,
        "month_average_buy": -1,
        "month_sold": -1,
        "month_bought": -1,
        "active_traders": -1,
        "month_highest_sell": -1,
        "month_lowest_buy": -1,
        "month_lowest_sell": -1,
        "month_highest_buy": -1,
        "buy_offers": -1,
        "sell_offers": -1,
        "day_average_sell": 61220,
        "day_average_buy": 53382,
        "day_sold": 2,
        "day_bought": 8,
        "day_highest_sell": 61220,
        "day_lowest_sell": 61220,
        "day_highest_buy": 56001,
        "day_lowest_buy": 52272,
        "total_immediate_profit": -1,
        "total_immediate_profit_info": ""
      },
      {
        "id": 22721,
        "time": 1763329413.0129535,
        "is_full_data": false,
        "buy_offer": -1,
        "sell_offer": -1,
        "month_average_sell": -1,
        "month_average_buy": -1,
        "month_sold": -1,
        "month_bought": -1,
        "active_traders": -1,
        "month_highest_sell": -1,
        "month_lowest_buy": -1,
        "month_lowest_sell": -1,
        "month_highest_buy": -1,
        "buy_offers": -1,
        "sell_offers": -1,
        "day_average_sell": 60603,
        "day_average_buy": 54624,
        "day_sold": 14,
        "day_bought": 5,
        "day_highest_sell": 61218,
        "day_lowest_sell": 59989,
        "day_highest_buy": 56001,
        "day_lowest_buy": 52555,
        "total_immediate_profit": -1,
        "total_immediate_profit_info": ""
      },
      {
        "id": 22721,
        "time": 1763415813.0129318,
        "is_full_data": false,
        "buy_offer": -1,
        "sell_offer": -1,
        "month_average_sell": -1,
        "month_average_buy": -1,
        "month_sold": -1,
        "month_bought": -1,
        "active_traders": -1,
        "month_highest_sell": -1,
        "month_lowest_buy": -1,
        "month_lowest_sell": -1,
        "month_highest_buy": -1,
        "buy_offers": -1,
        "sell_offers": -1,
        "day_average_sell": 59993,
        "day_average_buy": 53152,
        "day_sold": 3,
        "day_bought": 6,
        "day_highest_sell": 59995,
        "day_lowest_sell": 59993,
        "day_highest_buy": 53336,
        "day_lowest_buy": 52244,
        "total_immediate_profit": -1,
        "total_immediate_profit_info": ""
      },
      {
        "id": 22721,
        "time": 1764452658.0583367,
        "is_full_data": false,
        "buy_offer": -1,
        "sell_offer": -1,
        "month_average_sell": -1,
        "month_average_buy": -1,
        "month_sold": -1,
        "month_bought": -1,
        "active_traders": -1,
        "month_highest_sell": -1,
        "month_lowest_buy": -1,
        "month_lowest_sell": -1,
        "month_highest_buy": -1,
        "buy_offers": -1,
        "sell_offers": -1,
        "day_average_sell": 59110,
        "day_average_buy": 56000,
        "day_sold": 6,
        "day_bought": 2,
        "day_highest_sell": 59111,
        "day_lowest_sell": 59110,
        "day_highest_buy": 56001,
        "day_lowest_buy": 56000,
        "total_immediate_profit": -1,
        "total_immediate_profit_info": ""
      },
      {
        "id": 22721,
        "time": 1764539058.0582905,
        "is_full_data": false,
        "buy_offer": -1,
        "sell_offer": -1,
        "month_average_sell": -1,
        "month_average_buy": -1,
        "month_sold": -1,
        "month_bought": -1,
        "active_traders": -1,
        "month_highest_sell": -1,
        "month_lowest_buy": -1,
        "month_lowest_sell": -1,
        "month_highest_buy": -1,
        "buy_offers": -1,
        "sell_offers": -1,
        "day_average_sell": 58996,
        "day_average_buy": 53556,
        "day_sold": 6,
        "day_bought": 2,
        "day_highest_sell": 58997,
        "day_lowest_sell": 58996,
        "day_highest_buy": 53557,
        "day_lowest_buy": 53556,
        "total_immediate_profit": -1,
        "total_immediate_profit_info": ""
      },
      {
        "id": 22721,
        "time": 1764625458.0592687,
        "is_full_data": true,
        "buy_offer": 54501,
        "sell_offer": 58999,
        "month_average_sell": 60343,
        "month_average_buy": 52543,
        "month_sold": 209,
        "month_bought": 148,
        "active_traders": 14,
        "month_highest_sell": 65000,
        "month_lowest_buy": 48111,
        "month_lowest_sell": 57989,
        "month_highest_buy": 57002,
        "buy_offers": 18,
        "sell_offers": 14,
        "day_average_sell": 58997,
        "day_average_buy": 54500,
        "day_sold": 9,
        "day_bought": 2,
        "day_highest_sell": 58999,
        "day_lowest_sell": 58996,
        "day_highest_buy": 54501,
        "day_lowest_buy": 54500,
        "total_immediate_profit": 0,
        "total_immediate_profit_info": ""
      },
      {
        "id": 22721,
        "time": 1764711831.5716014,
        "is_full_data": false,
        "buy_offer": -1,
        "sell_offer": -1,
        "month_average_sell": -1,
        "month_average_buy": -1,
        "month_sold": -1,
        "month_bought": -1,
        "active_traders": -1,
        "month_highest_sell": -1,
        "month_lowest_buy": -1,
        "month_lowest_sell": -1,
        "month_highest_buy": -1,
        "buy_offers": -1,
        "sell_offers": -1,
        "day_average_sell": 58997,
        "day_average_buy": 54500,
        "day_sold": 8,
        "day_bought": 2,
        "day_highest_sell": 58999,
        "day_lowest_sell": 58996,
        "day_highest_buy": 54501,
        "day_lowest_buy": 54500,
        "total_immediate_profit": -1,
        "total_immediate_profit_info": ""
      },
      {
        "id": 22721,
        "time": 1764798231.5715642,
        "is_full_data": false,
        "buy_offer": -1,
        "sell_offer": -1,
        "month_average_sell": -1,
        "month_average_buy": -1,
        "month_sold": -1,
        "month_bought": -1,
        "active_traders": -1,
        "month_highest_sell": -1,
        "month_lowest_buy": -1,
        "month_lowest_sell": -1,
        "month_highest_buy": -1,
        "buy_offers": -1,
        "sell_offers": -1,
        "day_average_sell": 58998,
        "day_average_buy": 54500,
        "day_sold": 2,
        "day_bought": 2,
        "day_highest_sell": 58998,
        "day_lowest_sell": 58998,
        "day_highest_buy": 54501,
        "day_lowest_buy": 54500,
        "total_immediate_profit": -1,
        "total_immediate_profit_info": ""
      },
      {
        "id": 22721,
        "time": 1764884631.5715203,
        "is_full_data": false,
        "buy_offer": -1,
        "sell_offer": -1,
        "month_average_sell": -1,
        "month_average_buy": -1,
        "month_sold": -1,
        "month_bought": -1,
        "active_traders": -1,
        "month_highest_sell": -1,
        "month_lowest_buy": -1,
        "month_lowest_sell": -1,
        "month_highest_buy": -1,
        "buy_offers": -1,
        "sell_offers": -1,
        "day_average_sell": 59088,
        "day_average_buy": 53606,
        "day_sold": 16,
        "day_bought": 4,
        "day_highest_sell": 59123,
        "day_lowest_sell": 58998,
        "day_highest_buy": 53613,
        "day_lowest_buy": 53600,
        "total_immediate_profit": -1,
        "total_immediate_profit_info": ""
      },
      {
        "id": 22721,
        "time": 1765835054.6092453,
        "is_full_data": true,
        "buy_offer": 52005,
        "sell_offer": 61989,
        "month_average_sell": 60199,
        "month_average_buy": 51870,
        "month_sold": 234,
        "month_bought": 165,
        "active_traders": 8,
        "month_highest_sell": 65000,
        "month_lowest_buy": 48113,
        "month_lowest_sell": 57999,
        "month_highest_buy": 56001,
        "buy_offers": 15,
        "sell_offers": 8,
        "day_average_sell": 62000,
        "day_average_buy": 51021,
        "day_sold": 1,
        "day_bought": 12,
        "day_highest_sell": 62000,
        "day_lowest_sell": 62000,
        "day_highest_buy": 51024,
        "day_lowest_buy": 51016,
        "total_immediate_profit": 0,
        "total_immediate_profit_info": ""
      },
      {
        "id": 22721,
        "time": 1766007849.7066135,
        "is_full_data": false,
        "buy_offer": -1,
        "sell_offer": -1,
        "month_average_sell": -1,
        "month_average_buy": -1,
        "month_sold": -1,
        "month_bought": -1,
        "active_traders": -1,
        "month_highest_sell": -1,
        "month_lowest_buy": -1,
        "month_lowest_sell": -1,
        "month_highest_buy": -1,
        "buy_offers": -1,
        "sell_offers": -1,
        "day_average_sell": 62675,
        "day_average_buy": 52507,
        "day_sold": 11,
        "day_bought": 5,
        "day_highest_sell": 63500,
        "day_lowest_sell": 61984,
        "day_highest_buy": 52512,
        "day_lowest_buy": 52503,
        "total_immediate_profit": -1,
        "total_immediate_profit_info": ""
      },
      {
        "id": 22721,
        "time": 1766094249.70657,
        "is_full_data": false,
        "buy_offer": -1,
        "sell_offer": -1,
        "month_average_sell": -1,
        "month_average_buy": -1,
        "month_sold": -1,
        "month_bought": -1,
        "active_traders": -1,
        "month_highest_sell": -1,
        "month_lowest_buy": -1,
        "month_lowest_sell": -1,
        "month_highest_buy": -1,
        "buy_offers": -1,
        "sell_offers": -1,
        "day_average_sell": 63495,
        "day_average_buy": 55000,
        "day_sold": 6,
        "day_bought": 1,
        "day_highest_sell": 63498,
        "day_lowest_sell": 63493,
        "day_highest_buy": 55000,
        "day_lowest_buy": 55000,
        "total_immediate_profit": -1,
        "total_immediate_profit_info": ""
      },
      {
        "id": 22721,
        "time": 1766180649.706533,
        "is_full_data": false,
        "buy_offer": -1,
        "sell_offer": -1,
        "month_average_sell": -1,
        "month_average_buy": -1,
        "month_sold": -1,
        "month_bought": -1,
        "active_traders": -1,
        "month_highest_sell": -1,
        "month_lowest_buy": -1,
        "month_lowest_sell": -1,
        "month_highest_buy": -1,
        "buy_offers": -1,
        "sell_offers": -1,
        "day_average_sell": 63499,
        "day_average_buy": 57777,
        "day_sold": 7,
        "day_bought": 1,
        "day_highest_sell": 63500,
        "day_lowest_sell": 63498,
        "day_highest_buy": 57777,
        "day_lowest_buy": 57777,
        "total_immediate_profit": -1,
        "total_immediate_profit_info": ""
      },
      {
        "id": 22721,
        "time": 1766699062.734269,
        "is_full_data": false,
        "buy_offer": -1,
        "sell_offer": -1,
        "month_average_sell": -1,
        "month_average_buy": -1,
        "month_sold": -1,
        "month_bought": -1,
        "active_traders": -1,
        "month_highest_sell": -1,
        "month_lowest_buy": -1,
        "month_lowest_sell": -1,
        "month_highest_buy": -1,
        "buy_offers": -1,
        "sell_offers": -1,
        "day_average_sell": 77500,
        "day_average_buy": 57263,
        "day_sold": 2,
        "day_bought": 4,
        "day_highest_sell": 80000,
        "day_lowest_sell": 75000,
        "day_highest_buy": 57269,
        "day_lowest_buy": 57257,
        "total_immediate_profit": -1,
        "total_immediate_profit_info": ""
      },
      {
        "id": 22721,
        "time": 1766871862.7348664,
        "is_full_data": true,
        "buy_offer": 57326,
        "sell_offer": 74998,
        "month_average_sell": 63531,
        "month_average_buy": 53448,
        "month_sold": 232,
        "month_bought": 105,
        "active_traders": 9,
        "month_highest_sell": 80000,
        "month_lowest_buy": 48113,
        "month_lowest_sell": 58887,
        "month_highest_buy": 60001,
        "buy_offers": 29,
        "sell_offers": 9,
        "day_average_sell": 79899,
        "day_average_buy": 58651,
        "day_sold": 7,
        "day_bought": 4,
        "day_highest_sell": 79900,
        "day_lowest_sell": 79899,
        "day_highest_buy": 60001,
        "day_lowest_buy": 57301,
        "total_immediate_profit": 0,
        "total_immediate_profit_info": ""
      },
      {
        "id": 22721,
        "time": 1767132748.2369137,
        "is_full_data": false,
        "buy_offer": -1,
        "sell_offer": -1,
        "month_average_sell": -1,
        "month_average_buy": -1,
        "month_sold": -1,
        "month_bought": -1,
        "active_traders": -1,
        "month_highest_sell": -1,
        "month_lowest_buy": -1,
        "month_lowest_sell": -1,
        "month_highest_buy": -1,
        "buy_offers": -1,
        "sell_offers": -1,
        "day_average_sell": 74999,
        "day_average_buy": 57513,
        "day_sold": 4,
        "day_bought": 2,
        "day_highest_sell": 75000,
        "day_lowest_sell": 74998,
        "day_highest_buy": 57514,
        "day_lowest_buy": 57513,
        "total_immediate_profit": -1,
        "total_immediate_profit_info": ""
      },
      {
        "id": 22721,
        "time": 1767219148.236871,
        "is_full_data": false,
        "buy_offer": -1,
        "sell_offer": -1,
        "month_average_sell": -1,
        "month_average_buy": -1,
        "month_sold": -1,
        "month_bought": -1,
        "active_traders": -1,
        "month_highest_sell": -1,
        "month_lowest_buy": -1,
        "month_lowest_sell": -1,
        "month_highest_buy": -1,
        "buy_offers": -1,
        "sell_offers": -1,
        "day_average_sell": 74995,
        "day_average_buy": 60002,
        "day_sold": 3,
        "day_bought": 8,
        "day_highest_sell": 74998,
        "day_lowest_sell": 74990,
        "day_highest_buy": 60007,
        "day_lowest_buy": 60000,
        "total_immediate_profit": -1,
        "total_immediate_profit_info": ""
      },
      {
        "id": 22721,
        "time": 1767305548.236833,
        "is_full_data": false,
        "buy_offer": -1,
        "sell_offer": -1,
        "month_average_sell": -1,
        "month_average_buy": -1,
        "month_sold": -1,
        "month_bought": -1,
        "active_traders": -1,
        "month_highest_sell": -1,
        "month_lowest_buy": -1,
        "month_lowest_sell": -1,
        "month_highest_buy": -1,
        "buy_offers": -1,
        "sell_offers": -1,
        "day_average_sell": 74987,
        "day_average_buy": 60003,
        "day_sold": 4,
        "day_bought": 2,
        "day_highest_sell": 74989,
        "day_lowest_sell": 74986,
        "day_highest_buy": 60006,
        "day_lowest_buy": 60001,
        "total_immediate_profit": -1,
        "total_immediate_profit_info": ""
      },
      {
        "id": 22721,
        "time": 1767391948.2367954,
        "is_full_data": false,
        "buy_offer": -1,
        "sell_offer": -1,
        "month_average_sell": -1,
        "month_average_buy": -1,
        "month_sold": -1,
        "month_bought": -1,
        "active_traders": -1,
        "month_highest_sell": -1,
        "month_lowest_buy": -1,
        "month_lowest_sell": -1,
        "month_highest_buy": -1,
        "buy_offers": -1,
        "sell_offers": -1,
        "day_average_sell": 74994,
        "day_average_buy": 60005,
        "day_sold": 41,
        "day_bought": 6,
        "day_highest_sell": 75000,
        "day_lowest_sell": 74985,
        "day_highest_buy": 60007,
        "day_lowest_buy": 60002,
        "total_immediate_profit": -1,
        "total_immediate_profit_info": ""
      },
      {
        "id": 22721,
        "time": 1767478348.236753,
        "is_full_data": false,
        "buy_offer": -1,
        "sell_offer": -1,
        "month_average_sell": -1,
        "month_average_buy": -1,
        "month_sold": -1,
        "month_bought": -1,
        "active_traders": -1,
        "month_highest_sell": -1,
        "month_lowest_buy": -1,
        "month_lowest_sell": -1,
        "month_highest_buy": -1,
        "buy_offers": -1,
        "sell_offers": -1,
        "day_average_sell": 74441,
        "day_average_buy": 61006,
        "day_sold": 6,
        "day_bought": 2,
        "day_highest_sell": 74444,
        "day_lowest_sell": 74440,
        "day_highest_buy": 61007,
        "day_lowest_buy": 61006,
        "total_immediate_profit": -1,
        "total_immediate_profit_info": ""
      },
      {
        "id": 22721,
        "time": 1767564748.2379246,
        "is_full_data": true,
        "buy_offer": 63018,
        "sell_offer": 74442,
        "month_average_sell": 67870,
        "month_average_buy": 55604,
        "month_sold": 252,
        "month_bought": 106,
        "active_traders": 13,
        "month_highest_sell": 80000,
        "month_lowest_buy": 48113,
        "month_lowest_sell": 58887,
        "month_highest_buy": 63005,
        "buy_offers": 27,
        "sell_offers": 13,
        "day_average_sell": 74393,
        "day_average_buy": 63002,
        "day_sold": 9,
        "day_bought": 4,
        "day_highest_sell": 74444,
        "day_lowest_sell": 73999,
        "day_highest_buy": 63005,
        "day_lowest_buy": 63000,
        "total_immediate_profit": 0,
        "total_immediate_profit_info": ""
      },
      {
        "id": 22721,
        "time": 1767650240.3273234,
        "is_full_data": false,
        "buy_offer": -1,
        "sell_offer": -1,
        "month_average_sell": -1,
        "month_average_buy": -1,
        "month_sold": -1,
        "month_bought": -1,
        "active_traders": -1,
        "month_highest_sell": -1,
        "month_lowest_buy": -1,
        "month_lowest_sell": -1,
        "month_highest_buy": -1,
        "buy_offers": -1,
        "sell_offers": -1,
        "day_average_sell": 74205,
        "day_average_buy": 63339,
        "day_sold": 4,
        "day_bought": 3,
        "day_highest_sell": 74443,
        "day_lowest_sell": 73499,
        "day_highest_buy": 63501,
        "day_lowest_buy": 63018,
        "total_immediate_profit": -1,
        "total_immediate_profit_info": ""
      },
      {
        "id": 22721,
        "time": 1767823040.3272524,
        "is_full_data": false,
        "buy_offer": -1,
        "sell_offer": -1,
        "month_average_sell": -1,
        "month_average_buy": -1,
        "month_sold": -1,
        "month_bought": -1,
        "active_traders": -1,
        "month_highest_sell": -1,
        "month_lowest_buy": -1,
        "month_lowest_sell": -1,
        "month_highest_buy": -1,
        "buy_offers": -1,
        "sell_offers": -1,
        "day_average_sell": 73688,
        "day_average_buy": 66000,
        "day_sold": 5,
        "day_bought": 3,
        "day_highest_sell": 74442,
        "day_lowest_sell": 73500,
        "day_highest_buy": 66000,
        "day_lowest_buy": 66000,
        "total_immediate_profit": -1,
        "total_immediate_profit_info": ""
      },
      {
        "id": 22721,
        "time": 1767909440.3272164,
        "is_full_data": false,
        "buy_offer": -1,
        "sell_offer": -1,
        "month_average_sell": -1,
        "month_average_buy": -1,
        "month_sold": -1,
        "month_bought": -1,
        "active_traders": -1,
        "month_highest_sell": -1,
        "month_lowest_buy": -1,
        "month_lowest_sell": -1,
        "month_highest_buy": -1,
        "buy_offers": -1,
        "sell_offers": -1,
        "day_average_sell": 73146,
        "day_average_buy": 64744,
        "day_sold": 6,
        "day_bought": 10,
        "day_highest_sell": 74442,
        "day_lowest_sell": 70000,
        "day_highest_buy": 66006,
        "day_lowest_buy": 63000,
        "total_immediate_profit": -1,
        "total_immediate_profit_info": ""
      },
      {
        "id": 22721,
        "time": 1767995840.3271744,
        "is_full_data": false,
        "buy_offer": -1,
        "sell_offer": -1,
        "month_average_sell": -1,
        "month_average_buy": -1,
        "month_sold": -1,
        "month_bought": -1,
        "active_traders": -1,
        "month_highest_sell": -1,
        "month_lowest_buy": -1,
        "month_lowest_sell": -1,
        "month_highest_buy": -1,
        "buy_offers": -1,
        "sell_offers": -1,
        "day_average_sell": 69625,
        "day_average_buy": 58518,
        "day_sold": 14,
        "day_bought": 15,
        "day_highest_sell": 74442,
        "day_lowest_sell": 64989,
        "day_highest_buy": 63054,
        "day_lowest_buy": 55005,
        "total_immediate_profit": -1,
        "total_immediate_profit_info": ""
      },
      {
        "id": 22721,
        "time": 1768082240.3282716,
        "is_full_data": true,
        "buy_offer": 56011,
        "sell_offer": 64997,
        "month_average_sell": 69935,
        "month_average_buy": 58853,
        "month_sold": 241,
        "month_bought": 88,
        "active_traders": 13,
        "month_highest_sell": 80000,
        "month_lowest_buy": 51016,
        "month_lowest_sell": 59221,
        "month_highest_buy": 66006,
        "buy_offers": 13,
        "sell_offers": 14,
        "day_average_sell": 68919,
        "day_average_buy": 56114,
        "day_sold": 14,
        "day_bought": 3,
        "day_highest_sell": 74443,
        "day_lowest_sell": 65000,
        "day_highest_buy": 56117,
        "day_lowest_buy": 56113,
        "total_immediate_profit": 0,
        "total_immediate_profit_info": ""
      },
      {
        "id": 22721,
        "time": 1768167884.553328,
        "is_full_data": false,
        "buy_offer": -1,
        "sell_offer": -1,
        "month_average_sell": -1,
        "month_average_buy": -1,
        "month_sold": -1,
        "month_bought": -1,
        "active_traders": -1,
        "month_highest_sell": -1,
        "month_lowest_buy": -1,
        "month_lowest_sell": -1,
        "month_highest_buy": -1,
        "buy_offers": -1,
        "sell_offers": -1,
        "day_average_sell": 64997,
        "day_average_buy": 56090,
        "day_sold": 7,
        "day_bought": 5,
        "day_highest_sell": 65000,
        "day_lowest_sell": 64994,
        "day_highest_buy": 56116,
        "day_lowest_buy": 56010,
        "total_immediate_profit": -1,
        "total_immediate_profit_info": ""
      },
      {
        "id": 22721,
        "time": 1768254284.5533023,
        "is_full_data": false,
        "buy_offer": -1,
        "sell_offer": -1,
        "month_average_sell": -1,
        "month_average_buy": -1,
        "month_sold": -1,
        "month_bought": -1,
        "active_traders": -1,
        "month_highest_sell": -1,
        "month_lowest_buy": -1,
        "month_lowest_sell": -1,
        "month_highest_buy": -1,
        "buy_offers": -1,
        "sell_offers": -1,
        "day_average_sell": 64460,
        "day_average_buy": 58003,
        "day_sold": 13,
        "day_bought": 4,
        "day_highest_sell": 65000,
        "day_lowest_sell": 57990,
        "day_highest_buy": 60000,
        "day_lowest_buy": 56012,
        "total_immediate_profit": -1,
        "total_immediate_profit_info": ""
      },
      {
        "id": 22721,
        "time": 1768340684.5532813,
        "is_full_data": false,
        "buy_offer": -1,
        "sell_offer": -1,
        "month_average_sell": -1,
        "month_average_buy": -1,
        "month_sold": -1,
        "month_bought": -1,
        "active_traders": -1,
        "month_highest_sell": -1,
        "month_lowest_buy": -1,
        "month_lowest_sell": -1,
        "month_highest_buy": -1,
        "buy_offers": -1,
        "sell_offers": -1,
        "day_average_sell": 65000,
        "day_average_buy": 57717,
        "day_sold": 1,
        "day_bought": 7,
        "day_highest_sell": 65000,
        "day_lowest_sell": 65000,
        "day_highest_buy": 59999,
        "day_lowest_buy": 56000,
        "total_immediate_profit": -1,
        "total_immediate_profit_info": ""
      },
      {
        "id": 22721,
        "time": 1768513484.5532188,
        "is_full_data": false,
        "buy_offer": -1,
        "sell_offer": -1,
        "month_average_sell": -1,
        "month_average_buy": -1,
        "month_sold": -1,
        "month_bought": -1,
        "active_traders": -1,
        "month_highest_sell": -1,
        "month_lowest_buy": -1,
        "month_lowest_sell": -1,
        "month_highest_buy": -1,
        "buy_offers": -1,
        "sell_offers": -1,
        "day_average_sell": 68666,
        "day_average_buy": 59006,
        "day_sold": 3,
        "day_bought": 2,
        "day_highest_sell": 70000,
        "day_lowest_sell": 68000,
        "day_highest_buy": 59006,
        "day_lowest_buy": 59006,
        "total_immediate_profit": -1,
        "total_immediate_profit_info": ""
      },
      {
        "id": 22721,
        "time": 1768599884.5540516,
        "is_full_data": true,
        "buy_offer": 60128,
        "sell_offer": 69996,
        "month_average_sell": 70717,
        "month_average_buy": 59365,
        "month_sold": 231,
        "month_bought": 95,
        "active_traders": 14,
        "month_highest_sell": 80000,
        "month_lowest_buy": 55000,
        "month_lowest_sell": 57990,
        "month_highest_buy": 66006,
        "buy_offers": 15,
        "sell_offers": 14,
        "day_average_sell": 69997,
        "day_average_buy": 60034,
        "day_sold": 2,
        "day_bought": 6,
        "day_highest_sell": 69999,
        "day_lowest_sell": 69996,
        "day_highest_buy": 60036,
        "day_lowest_buy": 60031,
        "total_immediate_profit": 0,
        "total_immediate_profit_info": ""
      },
      {
        "id": 22721,
        "time": 1768686241.874705,
        "is_full_data": false,
        "buy_offer": -1,
        "sell_offer": -1,
        "month_average_sell": -1,
        "month_average_buy": -1,
        "month_sold": -1,
        "month_bought": -1,
        "active_traders": -1,
        "month_highest_sell": -1,
        "month_lowest_buy": -1,
        "month_lowest_sell": -1,
        "month_highest_buy": -1,
        "buy_offers": -1,
        "sell_offers": -1,
        "day_average_sell": 69993,
        "day_average_buy": 60126,
        "day_sold": 10,
        "day_bought": 1,
        "day_highest_sell": 69996,
        "day_lowest_sell": 69990,
        "day_highest_buy": 60126,
        "day_lowest_buy": 60126,
        "total_immediate_profit": -1,
        "total_immediate_profit_info": ""
      },
      {
        "id": 22721,
        "time": 1768859041.8746245,
        "is_full_data": false,
        "buy_offer": -1,
        "sell_offer": -1,
        "month_average_sell": -1,
        "month_average_buy": -1,
        "month_sold": -1,
        "month_bought": -1,
        "active_traders": -1,
        "month_highest_sell": -1,
        "month_lowest_buy": -1,
        "month_lowest_sell": -1,
        "month_highest_buy": -1,
        "buy_offers": -1,
        "sell_offers": -1,
        "day_average_sell": 69472,
        "day_average_buy": 60338,
        "day_sold": 12,
        "day_bought": 21,
        "day_highest_sell": 70000,
        "day_lowest_sell": 66999,
        "day_highest_buy": 60680,
        "day_lowest_buy": 59000,
        "total_immediate_profit": -1,
        "total_immediate_profit_info": ""
      },
      {
        "id": 22721,
        "time": 1769031841.8745444,
        "is_full_data": false,
        "buy_offer": -1,
        "sell_offer": -1,
        "month_average_sell": -1,
        "month_average_buy": -1,
        "month_sold": -1,
        "month_bought": -1,
        "active_traders": -1,
        "month_highest_sell": -1,
        "month_lowest_buy": -1,
        "month_lowest_sell": -1,
        "month_highest_buy": -1,
        "buy_offers": -1,
        "sell_offers": -1,
        "day_average_sell": 64774,
        "day_average_buy": 56210,
        "day_sold": 7,
        "day_bought": 3,
        "day_highest_sell": 64996,
        "day_lowest_sell": 64444,
        "day_highest_buy": 56211,
        "day_lowest_buy": 56210,
        "total_immediate_profit": -1,
        "total_immediate_profit_info": ""
      },
      {
        "id": 22721,
        "time": 1769204647.2161422,
        "is_full_data": false,
        "buy_offer": -1,
        "sell_offer": -1,
        "month_average_sell": -1,
        "month_average_buy": -1,
        "month_sold": -1,
        "month_bought": -1,
        "active_traders": -1,
        "month_highest_sell": -1,
        "month_lowest_buy": -1,
        "month_lowest_sell": -1,
        "month_highest_buy": -1,
        "buy_offers": -1,
        "sell_offers": -1,
        "day_average_sell": 62000,
        "day_average_buy": 56682,
        "day_sold": 2,
        "day_bought": 3,
        "day_highest_sell": 62000,
        "day_lowest_sell": 62000,
        "day_highest_buy": 56686,
        "day_lowest_buy": 56675,
        "total_immediate_profit": -1,
        "total_immediate_profit_info": ""
      },
      {
        "id": 22721,
        "time": 1769550247.216061,
        "is_full_data": false,
        "buy_offer": -1,
        "sell_offer": -1,
        "month_average_sell": -1,
        "month_average_buy": -1,
        "month_sold": -1,
        "month_bought": -1,
        "active_traders": -1,
        "month_highest_sell": -1,
        "month_lowest_buy": -1,
        "month_lowest_sell": -1,
        "month_highest_buy": -1,
        "buy_offers": -1,
        "sell_offers": -1,
        "day_average_sell": 63374,
        "day_average_buy": 56465,
        "day_sold": 12,
        "day_bought": 43,
        "day_highest_sell": 64500,
        "day_lowest_sell": 61999,
        "day_highest_buy": 57112,
        "day_lowest_buy": 56002,
        "total_immediate_profit": -1,
        "total_immediate_profit_info": ""
      },
      {
        "id": 22721,
        "time": 1769723115.267445,
        "is_full_data": false,
        "buy_offer": -1,
        "sell_offer": -1,
        "month_average_sell": -1,
        "month_average_buy": -1,
        "month_sold": -1,
        "month_bought": -1,
        "active_traders": -1,
        "month_highest_sell": -1,
        "month_lowest_buy": -1,
        "month_lowest_sell": -1,
        "month_highest_buy": -1,
        "buy_offers": -1,
        "sell_offers": -1,
        "day_average_sell": 63999,
        "day_average_buy": 56131,
        "day_sold": 10,
        "day_bought": 1,
        "day_highest_sell": 64000,
        "day_lowest_sell": 63999,
        "day_highest_buy": 56131,
        "day_lowest_buy": 56131,
        "total_immediate_profit": -1,
        "total_immediate_profit_info": ""
      },
      {
        "id": 22721,
        "time": 1769809515.2674253,
        "is_full_data": false,
        "buy_offer": -1,
        "sell_offer": -1,
        "month_average_sell": -1,
        "month_average_buy": -1,
        "month_sold": -1,
        "month_bought": -1,
        "active_traders": -1,
        "month_highest_sell": -1,
        "month_lowest_buy": -1,
        "month_lowest_sell": -1,
        "month_highest_buy": -1,
        "buy_offers": -1,
        "sell_offers": -1,
        "day_average_sell": 61008,
        "day_average_buy": 56176,
        "day_sold": 13,
        "day_bought": 7,
        "day_highest_sell": 64555,
        "day_lowest_sell": 59999,
        "day_highest_buy": 56500,
        "day_lowest_buy": 56112,
        "total_immediate_profit": -1,
        "total_immediate_profit_info": ""
      },
      {
        "id": 22721,
        "time": 1769895915.2674048,
        "is_full_data": false,
        "buy_offer": -1,
        "sell_offer": -1,
        "month_average_sell": -1,
        "month_average_buy": -1,
        "month_sold": -1,
        "month_bought": -1,
        "active_traders": -1,
        "month_highest_sell": -1,
        "month_lowest_buy": -1,
        "month_lowest_sell": -1,
        "month_highest_buy": -1,
        "buy_offers": -1,
        "sell_offers": -1,
        "day_average_sell": 64776,
        "day_average_buy": 58666,
        "day_sold": 4,
        "day_bought": 6,
        "day_highest_sell": 65000,
        "day_lowest_sell": 64550,
        "day_highest_buy": 58666,
        "day_lowest_buy": 58666,
        "total_immediate_profit": -1,
        "total_immediate_profit_info": ""
      },
      {
        "id": 22721,
        "time": 1769982315.2673795,
        "is_full_data": false,
        "buy_offer": -1,
        "sell_offer": -1,
        "month_average_sell": -1,
        "month_average_buy": -1,
        "month_sold": -1,
        "month_bought": -1,
        "active_traders": -1,
        "month_highest_sell": -1,
        "month_lowest_buy": -1,
        "month_lowest_sell": -1,
        "month_highest_buy": -1,
        "buy_offers": -1,
        "sell_offers": -1,
        "day_average_sell": 64999,
        "day_average_buy": 58672,
        "day_sold": 9,
        "day_bought": 1,
        "day_highest_sell": 67000,
        "day_lowest_sell": 64000,
        "day_highest_buy": 58672,
        "day_lowest_buy": 58672,
        "total_immediate_profit": -1,
        "total_immediate_profit_info": ""
      },
      {
        "id": 22721,
        "time": 1770068715.2673554,
        "is_full_data": false,
        "buy_offer": -1,
        "sell_offer": -1,
        "month_average_sell": -1,
        "month_average_buy": -1,
        "month_sold": -1,
        "month_bought": -1,
        "active_traders": -1,
        "month_highest_sell": -1,
        "month_lowest_buy": -1,
        "month_lowest_sell": -1,
        "month_highest_buy": -1,
        "buy_offers": -1,
        "sell_offers": -1,
        "day_average_sell": 63991,
        "day_average_buy": 59024,
        "day_sold": 18,
        "day_bought": 3,
        "day_highest_sell": 64000,
        "day_lowest_sell": 63988,
        "day_highest_buy": 59031,
        "day_lowest_buy": 59011,
        "total_immediate_profit": -1,
        "total_immediate_profit_info": ""
      },
      {
        "id": 22721,
        "time": 1770155115.2680008,
        "is_full_data": true,
        "buy_offer": 56675,
        "sell_offer": 64000,
        "month_average_sell": 66456,
        "month_average_buy": 58895,
        "month_sold": 241,
        "month_bought": 157,
        "active_traders": 12,
        "month_highest_sell": 74443,
        "month_lowest_buy": 55005,
        "month_lowest_sell": 57990,
        "month_highest_buy": 66006,
        "buy_offers": 16,
        "sell_offers": 12,
        "day_average_sell": 64405,
        "day_average_buy": 58736,
        "day_sold": 9,
        "day_bought": 10,
        "day_highest_sell": 66990,
        "day_lowest_sell": 63999,
        "day_highest_buy": 59011,
        "day_lowest_buy": 57666,
        "total_immediate_profit": 0,
        "total_immediate_profit_info": ""
      },
      {
        "id": 22721,
        "time": 1770414255.6016936,
        "is_full_data": false,
        "buy_offer": -1,
        "sell_offer": -1,
        "month_average_sell": -1,
        "month_average_buy": -1,
        "month_sold": -1,
        "month_bought": -1,
        "active_traders": -1,
        "month_highest_sell": -1,
        "month_lowest_buy": -1,
        "month_lowest_sell": -1,
        "month_highest_buy": -1,
        "buy_offers": -1,
        "sell_offers": -1,
        "day_average_sell": 64332,
        "day_average_buy": 56597,
        "day_sold": 8,
        "day_bought": 25,
        "day_highest_sell": 66660,
        "day_lowest_sell": 63998,
        "day_highest_buy": 58001,
        "day_lowest_buy": 55006,
        "total_immediate_profit": -1,
        "total_immediate_profit_info": ""
      },
      {
        "id": 22721,
        "time": 1770587055.6016457,
        "is_full_data": false,
        "buy_offer": -1,
        "sell_offer": -1,
        "month_average_sell": -1,
        "month_average_buy": -1,
        "month_sold": -1,
        "month_bought": -1,
        "active_traders": -1,
        "month_highest_sell": -1,
        "month_lowest_buy": -1,
        "month_lowest_sell": -1,
        "month_highest_buy": -1,
        "buy_offers": -1,
        "sell_offers": -1,
        "day_average_sell": 63490,
        "day_average_buy": 55569,
        "day_sold": 10,
        "day_bought": 1,
        "day_highest_sell": 66664,
        "day_lowest_sell": 62899,
        "day_highest_buy": 55569,
        "day_lowest_buy": 55569,
        "total_immediate_profit": -1,
        "total_immediate_profit_info": ""
      },
      {
        "id": 22721,
        "time": 1770673455.6022615,
        "is_full_data": true,
        "buy_offer": 56557,
        "sell_offer": 63331,
        "month_average_sell": 64927,
        "month_average_buy": 57674,
        "month_sold": 229,
        "month_bought": 160,
        "active_traders": 6,
        "month_highest_sell": 70000,
        "month_lowest_buy": 55006,
        "month_lowest_sell": 57990,
        "month_highest_buy": 60680,
        "buy_offers": 11,
        "sell_offers": 6,
        "day_average_sell": 63313,
        "day_average_buy": 55572,
        "day_sold": 8,
        "day_bought": 11,
        "day_highest_sell": 63331,
        "day_lowest_sell": 63293,
        "day_highest_buy": 55577,
        "day_lowest_buy": 55568,
        "total_immediate_profit": 0,
        "total_immediate_profit_info": ""
      },
      {
        "id": 22721,
        "time": 1770759837.0490847,
        "is_full_data": false,
        "buy_offer": -1,
        "sell_offer": -1,
        "month_average_sell": -1,
        "month_average_buy": -1,
        "month_sold": -1,
        "month_bought": -1,
        "active_traders": -1,
        "month_highest_sell": -1,
        "month_lowest_buy": -1,
        "month_lowest_sell": -1,
        "month_highest_buy": -1,
        "buy_offers": -1,
        "sell_offers": -1,
        "day_average_sell": 63329,
        "day_average_buy": 56335,
        "day_sold": 10,
        "day_bought": 7,
        "day_highest_sell": 63331,
        "day_lowest_sell": 63327,
        "day_highest_buy": 56667,
        "day_lowest_buy": 55671,
        "total_immediate_profit": -1,
        "total_immediate_profit_info": ""
      },
      {
        "id": 22721,
        "time": 1771105437.0489104,
        "is_full_data": false,
        "buy_offer": -1,
        "sell_offer": -1,
        "month_average_sell": -1,
        "month_average_buy": -1,
        "month_sold": -1,
        "month_bought": -1,
        "active_traders": -1,
        "month_highest_sell": -1,
        "month_lowest_buy": -1,
        "month_lowest_sell": -1,
        "month_highest_buy": -1,
        "buy_offers": -1,
        "sell_offers": -1,
        "day_average_sell": 66499,
        "day_average_buy": 57019,
        "day_sold": 10,
        "day_bought": 2,
        "day_highest_sell": 66500,
        "day_lowest_sell": 66498,
        "day_highest_buy": 57020,
        "day_lowest_buy": 57019,
        "total_immediate_profit": -1,
        "total_immediate_profit_info": ""
      },
      {
        "id": 22721,
        "time": 1771364625.1542294,
        "is_full_data": false,
        "buy_offer": -1,
        "sell_offer": -1,
        "month_average_sell": -1,
        "month_average_buy": -1,
        "month_sold": -1,
        "month_bought": -1,
        "active_traders": -1,
        "month_highest_sell": -1,
        "month_lowest_buy": -1,
        "month_lowest_sell": -1,
        "month_highest_buy": -1,
        "buy_offers": -1,
        "sell_offers": -1,
        "day_average_sell": 66499,
        "day_average_buy": 58035,
        "day_sold": 6,
        "day_bought": 3,
        "day_highest_sell": 66500,
        "day_lowest_sell": 66498,
        "day_highest_buy": 58036,
        "day_lowest_buy": 58035,
        "total_immediate_profit": -1,
        "total_immediate_profit_info": ""
      },
      {
        "id": 22721,
        "time": 1771623825.1541617,
        "is_full_data": false,
        "buy_offer": -1,
        "sell_offer": -1,
        "month_average_sell": -1,
        "month_average_buy": -1,
        "month_sold": -1,
        "month_bought": -1,
        "active_traders": -1,
        "month_highest_sell": -1,
        "month_lowest_buy": -1,
        "month_lowest_sell": -1,
        "month_highest_buy": -1,
        "buy_offers": -1,
        "sell_offers": -1,
        "day_average_sell": 66600,
        "day_average_buy": 60000,
        "day_sold": 2,
        "day_bought": 14,
        "day_highest_sell": 66600,
        "day_lowest_sell": 66600,
        "day_highest_buy": 60001,
        "day_lowest_buy": 60000,
        "total_immediate_profit": -1,
        "total_immediate_profit_info": ""
      },
      {
        "id": 22721,
        "time": 1771710225.1548114,
        "is_full_data": true,
        "buy_offer": 61001,
        "sell_offer": 66664,
        "month_average_sell": 64475,
        "month_average_buy": 57480,
        "month_sold": 240,
        "month_bought": 140,
        "active_traders": 2,
        "month_highest_sell": 67000,
        "month_lowest_buy": 55006,
        "month_lowest_sell": 59999,
        "month_highest_buy": 60001,
        "buy_offers": 12,
        "sell_offers": 2,
        "day_average_sell": 65933,
        "day_average_buy": 60000,
        "day_sold": 12,
        "day_bought": 3,
        "day_highest_sell": 66600,
        "day_lowest_sell": 64999,
        "day_highest_buy": 60001,
        "day_lowest_buy": 60000,
        "total_immediate_profit": 0,
        "total_immediate_profit_info": ""
      },
      {
        "id": 22721,
        "time": 1771797377.231429,
        "is_full_data": false,
        "buy_offer": -1,
        "sell_offer": -1,
        "month_average_sell": -1,
        "month_average_buy": -1,
        "month_sold": -1,
        "month_bought": -1,
        "active_traders": -1,
        "month_highest_sell": -1,
        "month_lowest_buy": -1,
        "month_lowest_sell": -1,
        "month_highest_buy": -1,
        "buy_offers": -1,
        "sell_offers": -1,
        "day_average_sell": 66663,
        "day_average_buy": 61000,
        "day_sold": 10,
        "day_bought": 2,
        "day_highest_sell": 66664,
        "day_lowest_sell": 66663,
        "day_highest_buy": 61001,
        "day_lowest_buy": 61000,
        "total_immediate_profit": -1,
        "total_immediate_profit_info": ""
      },
      {
        "id": 22721,
        "time": 1771883777.2314086,
        "is_full_data": false,
        "buy_offer": -1,
        "sell_offer": -1,
        "month_average_sell": -1,
        "month_average_buy": -1,
        "month_sold": -1,
        "month_bought": -1,
        "active_traders": -1,
        "month_highest_sell": -1,
        "month_lowest_buy": -1,
        "month_lowest_sell": -1,
        "month_highest_buy": -1,
        "buy_offers": -1,
        "sell_offers": -1,
        "day_average_sell": 66663,
        "day_average_buy": 60600,
        "day_sold": 4,
        "day_bought": 10,
        "day_highest_sell": 66664,
        "day_lowest_sell": 66663,
        "day_highest_buy": 61001,
        "day_lowest_buy": 60000,
        "total_immediate_profit": -1,
        "total_immediate_profit_info": ""
      },
      {
        "id": 22721,
        "time": 1772056577.2313628,
        "is_full_data": false,
        "buy_offer": -1,
        "sell_offer": -1,
        "month_average_sell": -1,
        "month_average_buy": -1,
        "month_sold": -1,
        "month_bought": -1,
        "active_traders": -1,
        "month_highest_sell": -1,
        "month_lowest_buy": -1,
        "month_lowest_sell": -1,
        "month_highest_buy": -1,
        "buy_offers": -1,
        "sell_offers": -1,
        "day_average_sell": 70333,
        "day_average_buy": 60667,
        "day_sold": 3,
        "day_bought": 5,
        "day_highest_sell": 75000,
        "day_lowest_sell": 68000,
        "day_highest_buy": 61114,
        "day_lowest_buy": 60000,
        "total_immediate_profit": -1,
        "total_immediate_profit_info": ""
      },
      {
        "id": 22721,
        "time": 1772142977.231342,
        "is_full_data": false,
        "buy_offer": -1,
        "sell_offer": -1,
        "month_average_sell": -1,
        "month_average_buy": -1,
        "month_sold": -1,
        "month_bought": -1,
        "active_traders": -1,
        "month_highest_sell": -1,
        "month_lowest_buy": -1,
        "month_lowest_sell": -1,
        "month_highest_buy": -1,
        "buy_offers": -1,
        "sell_offers": -1,
        "day_average_sell": 67998,
        "day_average_buy": 62000,
        "day_sold": 12,
        "day_bought": 2,
        "day_highest_sell": 68000,
        "day_lowest_sell": 67997,
        "day_highest_buy": 62001,
        "day_lowest_buy": 62000,
        "total_immediate_profit": -1,
        "total_immediate_profit_info": ""
      },
      {
        "id": 22721,
        "time": 1772229377.2313178,
        "is_full_data": false,
        "buy_offer": -1,
        "sell_offer": -1,
        "month_average_sell": -1,
        "month_average_buy": -1,
        "month_sold": -1,
        "month_bought": -1,
        "active_traders": -1,
        "month_highest_sell": -1,
        "month_lowest_buy": -1,
        "month_lowest_sell": -1,
        "month_highest_buy": -1,
        "buy_offers": -1,
        "sell_offers": -1,
        "day_average_sell": 69110,
        "day_average_buy": 58701,
        "day_sold": 9,
        "day_bought": 7,
        "day_highest_sell": 74999,
        "day_lowest_sell": 64999,
        "day_highest_buy": 61120,
        "day_lowest_buy": 55000,
        "total_immediate_profit": -1,
        "total_immediate_profit_info": ""
      },
      {
        "id": 22721,
        "time": 1772402177.2312713,
        "is_full_data": false,
        "buy_offer": -1,
        "sell_offer": -1,
        "month_average_sell": -1,
        "month_average_buy": -1,
        "month_sold": -1,
        "month_bought": -1,
        "active_traders": -1,
        "month_highest_sell": -1,
        "month_lowest_buy": -1,
        "month_lowest_sell": -1,
        "month_highest_buy": -1,
        "buy_offers": -1,
        "sell_offers": -1,
        "day_average_sell": 69687,
        "day_average_buy": 57794,
        "day_sold": 16,
        "day_bought": 3,
        "day_highest_sell": 70000,
        "day_lowest_sell": 68996,
        "day_highest_buy": 57801,
        "day_lowest_buy": 57781,
        "total_immediate_profit": -1,
        "total_immediate_profit_info": ""
      },
      {
        "id": 22721,
        "time": 1772488577.2312508,
        "is_full_data": false,
        "buy_offer": -1,
        "sell_offer": -1,
        "month_average_sell": -1,
        "month_average_buy": -1,
        "month_sold": -1,
        "month_bought": -1,
        "active_traders": -1,
        "month_highest_sell": -1,
        "month_lowest_buy": -1,
        "month_lowest_sell": -1,
        "month_highest_buy": -1,
        "buy_offers": -1,
        "sell_offers": -1,
        "day_average_sell": 69999,
        "day_average_buy": 60002,
        "day_sold": 5,
        "day_bought": 3,
        "day_highest_sell": 70000,
        "day_lowest_sell": 69999,
        "day_highest_buy": 60007,
        "day_lowest_buy": 60000,
        "total_immediate_profit": -1,
        "total_immediate_profit_info": ""
      },
      {
        "id": 22721,
        "time": 1772574977.2312298,
        "is_full_data": false,
        "buy_offer": -1,
        "sell_offer": -1,
        "month_average_sell": -1,
        "month_average_buy": -1,
        "month_sold": -1,
        "month_bought": -1,
        "active_traders": -1,
        "month_highest_sell": -1,
        "month_lowest_buy": -1,
        "month_lowest_sell": -1,
        "month_highest_buy": -1,
        "buy_offers": -1,
        "sell_offers": -1,
        "day_average_sell": 69999,
        "day_average_buy": 62105,
        "day_sold": 5,
        "day_bought": 16,
        "day_highest_sell": 70000,
        "day_lowest_sell": 69999,
        "day_highest_buy": 66001,
        "day_lowest_buy": 56666,
        "total_immediate_profit": -1,
        "total_immediate_profit_info": ""
      },
      {
        "id": 22721,
        "time": 1772747777.2311823,
        "is_full_data": false,
        "buy_offer": -1,
        "sell_offer": -1,
        "month_average_sell": -1,
        "month_average_buy": -1,
        "month_sold": -1,
        "month_bought": -1,
        "active_traders": -1,
        "month_highest_sell": -1,
        "month_lowest_buy": -1,
        "month_lowest_sell": -1,
        "month_highest_buy": -1,
        "buy_offers": -1,
        "sell_offers": -1,
        "day_average_sell": 69999,
        "day_average_buy": 56677,
        "day_sold": 5,
        "day_bought": 2,
        "day_highest_sell": 70000,
        "day_lowest_sell": 69999,
        "day_highest_buy": 56678,
        "day_lowest_buy": 56677,
        "total_immediate_profit": -1,
        "total_immediate_profit_info": ""
      },
      {
        "id": 22721,
        "time": 1772834177.2322214,
        "is_full_data": true,
        "buy_offer": 56564,
        "sell_offer": 67989,
        "month_average_sell": 66916,
        "month_average_buy": 58704,
        "month_sold": 225,
        "month_bought": 121,
        "active_traders": 8,
        "month_highest_sell": 75000,
        "month_lowest_buy": 55000,
        "month_lowest_sell": 62899,
        "month_highest_buy": 66001,
        "buy_offers": 8,
        "sell_offers": 9,
        "day_average_sell": 69615,
        "day_average_buy": 58004,
        "day_sold": 8,
        "day_bought": 5,
        "day_highest_sell": 69988,
        "day_lowest_sell": 68500,
        "day_highest_buy": 58008,
        "day_lowest_buy": 58000,
        "total_immediate_profit": 0,
        "total_immediate_profit_info": ""
      },
      {
        "id": 22721,
        "time": 1772921538.9589136,
        "is_full_data": false,
        "buy_offer": -1,
        "sell_offer": -1,
        "month_average_sell": -1,
        "month_average_buy": -1,
        "month_sold": -1,
        "month_bought": -1,
        "active_traders": -1,
        "month_highest_sell": -1,
        "month_lowest_buy": -1,
        "month_lowest_sell": -1,
        "month_highest_buy": -1,
        "buy_offers": -1,
        "sell_offers": -1,
        "day_average_sell": 69637,
        "day_average_buy": 57297,
        "day_sold": 17,
        "day_bought": 16,
        "day_highest_sell": 70000,
        "day_lowest_sell": 67996,
        "day_highest_buy": 58221,
        "day_lowest_buy": 56563,
        "total_immediate_profit": -1,
        "total_immediate_profit_info": ""
      },
      {
        "id": 22721,
        "time": 1773007938.9588768,
        "is_full_data": false,
        "buy_offer": -1,
        "sell_offer": -1,
        "month_average_sell": -1,
        "month_average_buy": -1,
        "month_sold": -1,
        "month_bought": -1,
        "active_traders": -1,
        "month_highest_sell": -1,
        "month_lowest_buy": -1,
        "month_lowest_sell": -1,
        "month_highest_buy": -1,
        "buy_offers": -1,
        "sell_offers": -1,
        "day_average_sell": 67928,
        "day_average_buy": 56563,
        "day_sold": 9,
        "day_bought": 2,
        "day_highest_sell": 67990,
        "day_lowest_sell": 67894,
        "day_highest_buy": 56564,
        "day_lowest_buy": 56563,
        "total_immediate_profit": -1,
        "total_immediate_profit_info": ""
      },
      {
        "id": 22721,
        "time": 1773094338.9588342,
        "is_full_data": false,
        "buy_offer": -1,
        "sell_offer": -1,
        "month_average_sell": -1,
        "month_average_buy": -1,
        "month_sold": -1,
        "month_bought": -1,
        "active_traders": -1,
        "month_highest_sell": -1,
        "month_lowest_buy": -1,
        "month_lowest_sell": -1,
        "month_highest_buy": -1,
        "buy_offers": -1,
        "sell_offers": -1,
        "day_average_sell": 67888,
        "day_average_buy": 57011,
        "day_sold": 8,
        "day_bought": 3,
        "day_highest_sell": 67890,
        "day_lowest_sell": 67884,
        "day_highest_buy": 57012,
        "day_lowest_buy": 57011,
        "total_immediate_profit": -1,
        "total_immediate_profit_info": ""
      },
      {
        "id": 22721,
        "time": 1773691568.5188005,
        "is_full_data": false,
        "buy_offer": -1,
        "sell_offer": -1,
        "month_average_sell": -1,
        "month_average_buy": -1,
        "month_sold": -1,
        "month_bought": -1,
        "active_traders": -1,
        "month_highest_sell": -1,
        "month_lowest_buy": -1,
        "month_lowest_sell": -1,
        "month_highest_buy": -1,
        "buy_offers": -1,
        "sell_offers": -1,
        "day_average_sell": 84897,
        "day_average_buy": 61026,
        "day_sold": 6,
        "day_bought": 4,
        "day_highest_sell": 84900,
        "day_lowest_sell": 84895,
        "day_highest_buy": 61027,
        "day_lowest_buy": 61026,
        "total_immediate_profit": -1,
        "total_immediate_profit_info": ""
      },
      {
        "id": 22721,
        "time": 1773777968.5187788,
        "is_full_data": false,
        "buy_offer": -1,
        "sell_offer": -1,
        "month_average_sell": -1,
        "month_average_buy": -1,
        "month_sold": -1,
        "month_bought": -1,
        "active_traders": -1,
        "month_highest_sell": -1,
        "month_lowest_buy": -1,
        "month_lowest_sell": -1,
        "month_highest_buy": -1,
        "buy_offers": -1,
        "sell_offers": -1,
        "day_average_sell": 84917,
        "day_average_buy": 60781,
        "day_sold": 5,
        "day_bought": 2,
        "day_highest_sell": 84990,
        "day_lowest_sell": 84899,
        "day_highest_buy": 61562,
        "day_lowest_buy": 60000,
        "total_immediate_profit": -1,
        "total_immediate_profit_info": ""
      },
      {
        "id": 22721,
        "time": 1773950768.5187244,
        "is_full_data": false,
        "buy_offer": -1,
        "sell_offer": -1,
        "month_average_sell": -1,
        "month_average_buy": -1,
        "month_sold": -1,
        "month_bought": -1,
        "active_traders": -1,
        "month_highest_sell": -1,
        "month_lowest_buy": -1,
        "month_lowest_sell": -1,
        "month_highest_buy": -1,
        "buy_offers": -1,
        "sell_offers": -1,
        "day_average_sell": 84987,
        "day_average_buy": 61569,
        "day_sold": 1,
        "day_bought": 10,
        "day_highest_sell": 84987,
        "day_lowest_sell": 84987,
        "day_highest_buy": 61579,
        "day_lowest_buy": 61567,
        "total_immediate_profit": -1,
        "total_immediate_profit_info": ""
      },
      {
        "id": 22721,
        "time": 1774209541.9747245,
        "is_full_data": false,
        "buy_offer": -1,
        "sell_offer": -1,
        "month_average_sell": -1,
        "month_average_buy": -1,
        "month_sold": -1,
        "month_bought": -1,
        "active_traders": -1,
        "month_highest_sell": -1,
        "month_lowest_buy": -1,
        "month_lowest_sell": -1,
        "month_highest_buy": -1,
        "buy_offers": -1,
        "sell_offers": -1,
        "day_average_sell": 84989,
        "day_average_buy": 61610,
        "day_sold": 8,
        "day_bought": 1,
        "day_highest_sell": 84990,
        "day_lowest_sell": 84989,
        "day_highest_buy": 61610,
        "day_lowest_buy": 61610,
        "total_immediate_profit": -1,
        "total_immediate_profit_info": ""
      },
      {
        "id": 22721,
        "time": 1774468741.9746602,
        "is_full_data": false,
        "buy_offer": -1,
        "sell_offer": -1,
        "month_average_sell": -1,
        "month_average_buy": -1,
        "month_sold": -1,
        "month_bought": -1,
        "active_traders": -1,
        "month_highest_sell": -1,
        "month_lowest_buy": -1,
        "month_lowest_sell": -1,
        "month_highest_buy": -1,
        "buy_offers": -1,
        "sell_offers": -1,
        "day_average_sell": 85000,
        "day_average_buy": 64318,
        "day_sold": 1,
        "day_bought": 2,
        "day_highest_sell": 85000,
        "day_lowest_sell": 85000,
        "day_highest_buy": 67000,
        "day_lowest_buy": 61637,
        "total_immediate_profit": -1,
        "total_immediate_profit_info": ""
      },
      {
        "id": 22721,
        "time": 1774811079.7342281,
        "is_full_data": false,
        "buy_offer": -1,
        "sell_offer": -1,
        "month_average_sell": -1,
        "month_average_buy": -1,
        "month_sold": -1,
        "month_bought": -1,
        "active_traders": -1,
        "month_highest_sell": -1,
        "month_lowest_buy": -1,
        "month_lowest_sell": -1,
        "month_highest_buy": -1,
        "buy_offers": -1,
        "sell_offers": -1,
        "day_average_sell": 87758,
        "day_average_buy": 70009,
        "day_sold": 15,
        "day_bought": 11,
        "day_highest_sell": 88900,
        "day_lowest_sell": 86993,
        "day_highest_buy": 70020,
        "day_lowest_buy": 70000,
        "total_immediate_profit": -1,
        "total_immediate_profit_info": ""
      },
      {
        "id": 22721,
        "time": 1775243079.734852,
        "is_full_data": true,
        "buy_offer": 75555,
        "sell_offer": 88000,
        "month_average_sell": 81493,
        "month_average_buy": 61260,
        "month_sold": 151,
        "month_bought": 75,
        "active_traders": 7,
        "month_highest_sell": 93000,
        "month_lowest_buy": 56563,
        "month_lowest_sell": 67665,
        "month_highest_buy": 74132,
        "buy_offers": 27,
        "sell_offers": 7,
        "day_average_sell": 84997,
        "day_average_buy": 74127,
        "day_sold": 3,
        "day_bought": 11,
        "day_highest_sell": 84998,
        "day_lowest_sell": 84996,
        "day_highest_buy": 74132,
        "day_lowest_buy": 74125,
        "total_immediate_profit": 0,
        "total_immediate_profit_info": ""
      },
      {
        "id": 22721,
        "time": 1775501946.1402698,
        "is_full_data": false,
        "buy_offer": -1,
        "sell_offer": -1,
        "month_average_sell": -1,
        "month_average_buy": -1,
        "month_sold": -1,
        "month_bought": -1,
        "active_traders": -1,
        "month_highest_sell": -1,
        "month_lowest_buy": -1,
        "month_lowest_sell": -1,
        "month_highest_buy": -1,
        "buy_offers": -1,
        "sell_offers": -1,
        "day_average_sell": 79962,
        "day_average_buy": 75556,
        "day_sold": 6,
        "day_bought": 5,
        "day_highest_sell": 80000,
        "day_lowest_sell": 79888,
        "day_highest_buy": 75560,
        "day_lowest_buy": 75555,
        "total_immediate_profit": -1,
        "total_immediate_profit_info": ""
      },
      {
        "id": 22721,
        "time": 1775588346.14023,
        "is_full_data": false,
        "buy_offer": -1,
        "sell_offer": -1,
        "month_average_sell": -1,
        "month_average_buy": -1,
        "month_sold": -1,
        "month_bought": -1,
        "active_traders": -1,
        "month_highest_sell": -1,
        "month_lowest_buy": -1,
        "month_lowest_sell": -1,
        "month_highest_buy": -1,
        "buy_offers": -1,
        "sell_offers": -1,
        "day_average_sell": 81842,
        "day_average_buy": 75287,
        "day_sold": 17,
        "day_bought": 4,
        "day_highest_sell": 85000,
        "day_lowest_sell": 79999,
        "day_highest_buy": 75556,
        "day_lowest_buy": 75000,
        "total_immediate_profit": -1,
        "total_immediate_profit_info": ""
      },
      {
        "id": 22721,
        "time": 1775761146.140145,
        "is_full_data": false,
        "buy_offer": -1,
        "sell_offer": -1,
        "month_average_sell": -1,
        "month_average_buy": -1,
        "month_sold": -1,
        "month_bought": -1,
        "active_traders": -1,
        "month_highest_sell": -1,
        "month_lowest_buy": -1,
        "month_lowest_sell": -1,
        "month_highest_buy": -1,
        "buy_offers": -1,
        "sell_offers": -1,
        "day_average_sell": 83599,
        "day_average_buy": 75123,
        "day_sold": 5,
        "day_bought": 9,
        "day_highest_sell": 84000,
        "day_lowest_sell": 82999,
        "day_highest_buy": 75562,
        "day_lowest_buy": 74121,
        "total_immediate_profit": -1,
        "total_immediate_profit_info": ""
      }
    ]
  ],
  "_outlier_cleanup": {
    "version": 1,
    "lower_percentile": 1.5,
    "upper_percentile": 98.5,
    "window_size": 0,
    "accepted_fingerprints": [
      "0588dea5120dda96",
      "05e6cea3ab45bf6e",
      "0b1e9dd8b502f6e7",
      "0bad013b0f21c303",
      "0c6ac95d843e6260",
      "0c7876a6a5d75305",
      "0d192df5d06a30b2",
      "0e872ec506a06991",
      "1126de993897fa88",
      "16ec4ceefebfd82d",
      "19ece668bd1b7473",
      "1a8cf623229916f3",
      "1c5303301f8ef898",
      "256c891d525a1033",
      "2f492bcf38febdc8",
      "36444e68505a1222",
      "375fb5b94c7091f4",
      "38decd597876c3b7",
      "3cd85fa6a2163470",
      "3da2652261e31d14",
      "40708e5109c70654",
      "41b5d65990db62ba",
      "499c2f519731b0b3",
      "4d1e0bdd2ce08c26",
      "4e4bebd114254a65",
      "5348596e89148d91",
      "5530406f931d4e3b",
      "55db9f5fe90c73f8",
      "58957962c0465014",
      "58c48efb646c0327",
      "59510e55fefe1504",
      "59ca63cbfa8f92be",
      "5d939cbd55d8b0e9",
      "6600b877ecc58d8d",
      "6742938712bfd076",
      "6a3b15cede9e3722",
      "6c196a29172262a3",
      "6ef0fc390d40e034",
      "7053454066246776",
      "740226307ad0b486",
      "7c856134f19b4e95",
      "7f9eef1b759ab445",
      "833da7faf83339d1",
      "90685cbdd74fd7c7",
      "96f14b44ca77e8ff",
      "99328d25743ce7ae",
      "a0c0a4b63300795e",
      "a2e8eda56da6b51f",
      "a492667532f6a686",
      "a62867411c83d44c",
      "a69821b003b1ad03",
      "a6d045ee2c794949",
      "afb0b8dc6d07f003",
      "b02321fbb42b2abb",
      "b11028369cb6e270",
      "b6d9a03006773e57",
      "b810eb00b3d2f3ff",
      "b9d6c56bc7e0ef07",
      "c517a1aed420abfd",
      "c70cdd7e658f8ff1",
      "cc280f27092a8879",
      "cd92160f7da57291",
      "ce8fbe87f8357d91",
      "d092aeeac1d0fc72",
      "d0d78acaef2d78d1",
      "d3b0e432e1c0f325",
      "d59be3fd9b9ca76a",
      "da68736cd5e8cd79",
      "e0b3d832d2a54055",
      "e4553168545abb54",
      "e4f1f50676341a8b",
      "e65b549ac7911623",
      "e9d38cefd696115a",
      "ec987520200f43d7",
      "f0b14f2ca44d4a5a",
      "f26b51dcf9b61039",
      "fd0d1ecd6487ef9d",
      "fd10b978e3134a84"
    ],
    "rejected_fingerprints": [
      "00bfb52862994933",
      "09cbb1f6fc189ef6",
      "0ff656dbc77763a7",
      "19b3e088e432b94f",
      "1b7a959aaf053226",
      "220c3e54a3b2e8c4",
      "35257e86774afa4c",
      "3cae16f4c9acf2cb",
      "49a4b86f8ea40611",
      "5d77053110104ee2",
      "7701d16ac2477fcc",
      "a23243dbffa1ab98",
      "ccb1ef6f162fdc05",
      "df6d31723a5705da",
      "e0ca4e58c6425070",
      "f2a223fca1c450f8",
      "fa78088aa08b3d9b",
      "fd67c7586c54b82c"
    ]
  }
}
